{
  "annotations": {
    "list": [
      {
        "builtIn": 1,
        "datasource": {
          "type": "grafana",
          "uid": "-- Grafana --"
        },
        "enable": true,
        "hide": true,
        "iconColor": "rgba(0, 211, 255, 1)",
        "name": "Annotations & Alerts",
        "type": "dashboard"
      }
    ]
  },
  "editable": true,
  "fiscalYearStartMonth": 0,
  "graphTooltip": 0,
  "id": 1,
  "links": [],
  "panels": [
    {
      "datasource": {
        "type": "prometheus",
        "uid": "PBFA97CFB590B2093"
      },
      "description": "Latest poll height our validator voted on. Should continuously increase. Use this for alerting if it stops increasing.",
      "fieldConfig": {
        "defaults": {
          "color": {
            "mode": "thresholds"
          },
          "mappings": [],
          "thresholds": {
            "mode": "absolute",
            "steps": [
              {
                "color": "green",
                "value": 0
              }
            ]
          },
          "unit": "short"
        },
        "overrides": []
      },
      "gridPos": {
        "h": 6,
        "w": 6,
        "x": 0,
        "y": 0
      },
      "id": 1,
      "options": {
        "colorMode": "value",
        "graphMode": "area",
        "justifyMode": "auto",
        "orientation": "auto",
        "percentChangeColorMode": "standard",
        "reduceOptions": {
          "calcs": [
            "lastNotNull"
          ],
          "fields": "",
          "values": false
        },
        "showPercentChange": false,
        "textMode": "auto",
        "wideLayout": true
      },
      "pluginVersion": "12.2.0-17027759091",
      "targets": [
        {
          "datasource": {
            "type": "prometheus",
            "uid": "PBFA97CFB590B2093"
          },
          "editorMode": "code",
          "expr": "rcosmos_axelar_evm_votes_latest_height{alerts=\"true\",network=~\"$network\",validator_address=~\"$validator_address\"}",
          "legendFormat": "Our Validator Latest Height",
          "range": true,
          "refId": "A"
        }
      ],
      "title": "Our Validator - Latest Poll Height",
      "type": "stat"
    },
    {
      "datasource": {
        "type": "prometheus",
        "uid": "PBFA97CFB590B2093"
      },
      "description": "Cumulative total votes cast by our validator",
      "fieldConfig": {
        "defaults": {
          "color": {
            "mode": "thresholds"
          },
          "mappings": [],
          "thresholds": {
            "mode": "absolute",
            "steps": [
              {
                "color": "green",
                "value": 0
              }
            ]
          },
          "unit": "short"
        },
        "overrides": []
      },
      "gridPos": {
        "h": 6,
        "w": 6,
        "x": 6,
        "y": 0
      },
      "id": 2,
      "options": {
        "colorMode": "value",
        "graphMode": "area",
        "justifyMode": "auto",
        "orientation": "auto",
        "percentChangeColorMode": "standard",
        "reduceOptions": {
          "calcs": [
            "lastNotNull"
          ],
          "fields": "",
          "values": false
        },
        "showPercentChange": false,
        "textMode": "auto",
        "wideLayout": true
      },
      "pluginVersion": "12.2.0-17027759091",
      "targets": [
        {
          "datasource": {
            "type": "prometheus",
            "uid": "PBFA97CFB590B2093"
          },
          "editorMode": "code",
          "expr": "sum(rcosmos_axelar_evm_votes_total{alerts=\"true\",network=~\"$network\",validator_address=~\"$validator_address\"})",
          "legendFormat": "Total Votes",
          "range": true,
          "refId": "A"
        }
      ],
      "title": "Our Validator - Total Votes",
      "type": "stat"
    },
    {
      "datasource": {
        "type": "prometheus",
        "uid": "PBFA97CFB590B2093"
      },
      "description": "Percentage of votes that were Yes",
      "fieldConfig": {
        "defaults": {
          "color": {
            "mode": "thresholds"
          },
          "mappings": [],
          "thresholds": {
            "mode": "absolute",
            "steps": [
              {
                "color": "green",
                "value": 0
              }
            ]
          },
          "unit": "short"
        },
        "overrides": []
      },
      "gridPos": {
        "h": 6,
        "w": 6,
        "x": 12,
        "y": 0
      },
      "id": 3,
      "options": {
        "colorMode": "value",
        "graphMode": "area",
        "justifyMode": "auto",
        "orientation": "auto",
        "percentChangeColorMode": "standard",
        "reduceOptions": {
          "calcs": [
            "lastNotNull"
          ],
          "fields": "",
          "values": false
        },
        "showPercentChange": false,
        "textMode": "auto",
        "wideLayout": true
      },
      "pluginVersion": "12.2.0-17027759091",
      "targets": [
        {
          "datasource": {
            "type": "prometheus",
            "uid": "PBFA97CFB590B2093"
          },
          "editorMode": "code",
          "expr": "sum(rcosmos_axelar_evm_votes_yes{alerts=\"true\",network=~\"$network\",validator_address=~\"$validator_address\"}) / sum(rcosmos_axelar_evm_votes_total{alerts=\"true\",network=~\"$network\",validator_address=~\"$validator_address\"}) * 100",
          "legendFormat": "Yes Vote %",
          "range": true,
          "refId": "A"
        }
      ],
      "title": "Our Validator - Yes Vote %",
      "type": "stat"
    },
    {
      "datasource": {
        "type": "prometheus",
        "uid": "PBFA97CFB590B2093"
      },
      "description": "Rate of poll height increase. Should be > 0 if voting. Alert if == 0 for > 5 minutes.",
      "fieldConfig": {
        "defaults": {
          "color": {
            "mode": "thresholds"
          },
          "mappings": [],
          "thresholds": {
            "mode": "absolute",
            "steps": [
              {
                "color": "green",
                "value": 0
              },
              {
                "color": "yellow",
                "value": 300
              },
              {
                "color": "red",
                "value": 600
              }
            ]
          },
          "unit": "s"
        },
        "overrides": []
      },
      "gridPos": {
        "h": 6,
        "w": 6,
        "x": 18,
        "y": 0
      },
      "id": 4,
      "options": {
        "colorMode": "value",
        "graphMode": "area",
        "justifyMode": "auto",
        "orientation": "auto",
        "percentChangeColorMode": "standard",
        "reduceOptions": {
          "calcs": [
            "lastNotNull"
          ],
          "fields": "",
          "values": false
        },
        "showPercentChange": false,
        "textMode": "auto",
        "wideLayout": true
      },
      "pluginVersion": "12.2.0-17027759091",
      "targets": [
        {
          "datasource": {
            "type": "prometheus",
            "uid": "PBFA97CFB590B2093"
          },
          "editorMode": "code",
          "expr": "deriv(rcosmos_axelar_evm_votes_latest_height{alerts=\"true\",network=~\"$network\",validator_address=~\"$validator_address\"}[5m])",
          "legendFormat": "Height Increase Rate",
          "range": true,
          "refId": "A"
        }
      ],
      "title": "Height Increase Rate (polls/sec)",
      "type": "stat"
    },
    {
      "datasource": {
        "type": "prometheus",
        "uid": "PBFA97CFB590B2093"
      },
      "description": "This should show a continuous linear uptrend. If our validator's line stops increasing, voting has stopped. Use this metric for alerting: `increase(rcosmos_axelar_evm_votes_latest_height{alerts=\"true\"}[5m]) == 0`",
      "fieldConfig": {
        "defaults": {
          "color": {
            "mode": "palette-classic"
          },
          "custom": {
            "axisBorderShow": false,
            "axisCenteredZero": false,
            "axisColorMode": "text",
            "axisLabel": "Poll Height",
            "axisPlacement": "auto",
            "barAlignment": 0,
            "barWidthFactor": 0.6,
            "drawStyle": "line",
            "fillOpacity": 10,
            "gradientMode": "none",
            "hideFrom": {
              "legend": false,
              "tooltip": false,
              "viz": false
            },
            "insertNulls": false,
            "lineInterpolation": "linear",
            "lineWidth": 2,
            "pointSize": 5,
            "scaleDistribution": {
              "type": "linear"
            },
            "showPoints": "never",
            "spanNulls": false,
            "stacking": {
              "group": "A",
              "mode": "none"
            },
            "thresholdsStyle": {
              "mode": "off"
            }
          },
          "mappings": [],
          "thresholds": {
            "mode": "absolute",
            "steps": [
              {
                "color": "green",
                "value": 0
              }
            ]
          },
          "unit": "short"
        },
        "overrides": [
          {
            "matcher": {
              "id": "byRegexp",
              "options": "/alerts=\"true\"/"
            },
            "properties": [
              {
                "id": "color",
                "value": {
                  "fixedColor": "red",
                  "mode": "fixed"
                }
              },
              {
                "id": "custom.lineWidth",
                "value": 3
              }
            ]
          }
        ]
      },
      "gridPos": {
        "h": 10,
        "w": 24,
        "x": 0,
        "y": 6
      },
      "id": 5,
      "options": {
        "legend": {
          "calcs": [
            "lastNotNull",
            "max"
          ],
          "displayMode": "table",
          "placement": "bottom",
          "showLegend": true
        },
        "tooltip": {
          "hideZeros": false,
          "mode": "multi",
          "sort": "desc"
        }
      },
      "pluginVersion": "12.2.0-17027759091",
      "targets": [
        {
          "datasource": {
            "type": "prometheus",
            "uid": "PBFA97CFB590B2093"
          },
          "editorMode": "code",
          "expr": "rcosmos_axelar_evm_votes_latest_height{alerts=\"true\",network=~\"$network\",validator_address=~\"$validator_address\"}",
          "legendFormat": "Our Validator ({{validator_address}})",
          "range": true,
          "refId": "A"
        },
        {
          "datasource": {
            "type": "prometheus",
            "uid": "PBFA97CFB590B2093"
          },
          "editorMode": "code",
          "expr": "rcosmos_axelar_evm_votes_latest_height{alerts=\"false\",network=~\"$network\",validator_address=~\"$validator_address\"}",
          "legendFormat": "{{validator_address}}",
          "range": true,
          "refId": "B"
        }
      ],
      "title": "Latest Poll Height by Validator (Linear Uptrend - Alert Metric)",
      "type": "timeseries"
    },
    {
      "datasource": {
        "type": "prometheus",
        "uid": "PBFA97CFB590B2093"
      },
      "description": "This shows votes missed by moniker",
      "fieldConfig": {
        "defaults": {
          "color": {
            "mode": "palette-classic"
          },
          "custom": {
            "axisBorderShow": false,
            "axisCenteredZero": false,
            "axisColorMode": "text",
            "axisLabel": "missed votes",
            "axisPlacement": "auto",
            "barAlignment": 0,
            "barWidthFactor": 0.6,
            "drawStyle": "line",
            "fillOpacity": 10,
            "gradientMode": "none",
            "hideFrom": {
              "legend": false,
              "tooltip": false,
              "viz": false
            },
            "insertNulls": false,
            "lineInterpolation": "linear",
            "lineWidth": 2,
            "pointSize": 5,
            "scaleDistribution": {
              "type": "linear"
            },
            "showPoints": "never",
            "spanNulls": false,
            "stacking": {
              "group": "A",
              "mode": "none"
            },
            "thresholdsStyle": {
              "mode": "off"
            }
          },
          "mappings": [],
          "thresholds": {
            "mode": "absolute",
            "steps": [
              {
                "color": "green",
                "value": 0
              }
            ]
          },
          "unit": "short"
        },
        "overrides": [
          {
            "matcher": {
              "id": "byRegexp",
              "options": "/alerts=\"true\"/"
            },
            "properties": [
              {
                "id": "color",
                "value": {
                  "fixedColor": "red",
                  "mode": "fixed"
                }
              },
              {
                "id": "custom.lineWidth",
                "value": 3
              }
            ]
          }
        ]
      },
      "gridPos": {
        "h": 10,
        "w": 24,
        "x": 0,
        "y": 16
      },
      "id": 15,
      "options": {
        "legend": {
          "calcs": [
            "lastNotNull",
            "max"
          ],
          "displayMode": "table",
          "placement": "bottom",
          "showLegend": true
        },
        "tooltip": {
          "hideZeros": false,
          "mode": "multi",
          "sort": "desc"
        }
      },
      "pluginVersion": "12.2.0-17027759091",
      "targets": [
        {
          "datasource": {
            "type": "prometheus",
            "uid": "PBFA97CFB590B2093"
          },
          "editorMode": "code",
          "expr": "increase(rcosmos_axelar_evm_votes_missed{network=~\"$network\",validator_address=~\"$validator_address\",moniker=~\".*\"}[5m]) > 0",
          "legendFormat": "{{moniker}}",
          "range": true,
          "refId": "A"
        }
      ],
      "title": "EVM votes missed",
      "type": "timeseries"
    },
    {
      "datasource": {
        "type": "prometheus",
        "uid": "PBFA97CFB590B2093"
      },
      "description": "Cumulative total votes. Note: resets on exporter restart.",
      "fieldConfig": {
        "defaults": {
          "color": {
            "mode": "palette-classic"
          },
          "custom": {
            "axisBorderShow": false,
            "axisCenteredZero": false,
            "axisColorMode": "text",
            "axisLabel": "Total Votes",
            "axisPlacement": "auto",
            "barAlignment": 0,
            "barWidthFactor": 0.6,
            "drawStyle": "line",
            "fillOpacity": 10,
            "gradientMode": "none",
            "hideFrom": {
              "legend": false,
              "tooltip": false,
              "viz": false
            },
            "insertNulls": false,
            "lineInterpolation": "linear",
            "lineWidth": 2,
            "pointSize": 5,
            "scaleDistribution": {
              "type": "linear"
            },
            "showPoints": "never",
            "spanNulls": false,
            "stacking": {
              "group": "A",
              "mode": "none"
            },
            "thresholdsStyle": {
              "mode": "off"
            }
          },
          "mappings": [],
          "thresholds": {
            "mode": "absolute",
            "steps": [
              {
                "color": "green",
                "value": 0
              }
            ]
          },
          "unit": "short"
        },
        "overrides": [
          {
            "matcher": {
              "id": "byRegexp",
              "options": "/alerts=\"true\"/"
            },
            "properties": [
              {
                "id": "color",
                "value": {
                  "fixedColor": "red",
                  "mode": "fixed"
                }
              },
              {
                "id": "custom.lineWidth",
                "value": 3
              }
            ]
          }
        ]
      },
      "gridPos": {
        "h": 8,
        "w": 12,
        "x": 0,
        "y": 26
      },
      "id": 6,
      "options": {
        "legend": {
          "calcs": [
            "lastNotNull",
            "max"
          ],
          "displayMode": "table",
          "placement": "bottom",
          "showLegend": true
        },
        "tooltip": {
          "hideZeros": false,
          "mode": "multi",
          "sort": "desc"
        }
      },
      "pluginVersion": "12.2.0-17027759091",
      "targets": [
        {
          "datasource": {
            "type": "prometheus",
            "uid": "PBFA97CFB590B2093"
          },
          "editorMode": "code",
          "expr": "sum(rcosmos_axelar_evm_votes_total{alerts=\"true\",network=~\"$network\",validator_address=~\"$validator_address\"}) by (validator_address)",
          "legendFormat": "Our Validator ({{validator_address}})",
          "range": true,
          "refId": "A"
        },
        {
          "datasource": {
            "type": "prometheus",
            "uid": "PBFA97CFB590B2093"
          },
          "editorMode": "code",
          "expr": "sum(rcosmos_axelar_evm_votes_total{alerts=\"false\",network=~\"$network\",validator_address=~\"$validator_address\"}) by (validator_address)",
          "legendFormat": "{{validator_address}}",
          "range": true,
          "refId": "B"
        }
      ],
      "title": "Total Votes by Validator",
      "type": "timeseries"
    },
    {
      "datasource": {
        "type": "prometheus",
        "uid": "PBFA97CFB590B2093"
      },
      "description": "Rate of voting over time. Should be relatively constant if voting consistently.",
      "fieldConfig": {
        "defaults": {
          "color": {
            "mode": "palette-classic"
          },
          "custom": {
            "axisBorderShow": false,
            "axisCenteredZero": false,
            "axisColorMode": "text",
            "axisLabel": "Votes per Minute",
            "axisPlacement": "auto",
            "barAlignment": 0,
            "barWidthFactor": 0.6,
            "drawStyle": "line",
            "fillOpacity": 10,
            "gradientMode": "none",
            "hideFrom": {
              "legend": false,
              "tooltip": false,
              "viz": false
            },
            "insertNulls": false,
            "lineInterpolation": "linear",
            "lineWidth": 2,
            "pointSize": 5,
            "scaleDistribution": {
              "type": "linear"
            },
            "showPoints": "never",
            "spanNulls": false,
            "stacking": {
              "group": "A",
              "mode": "none"
            },
            "thresholdsStyle": {
              "mode": "off"
            }
          },
          "mappings": [],
          "thresholds": {
            "mode": "absolute",
            "steps": [
              {
                "color": "green",
                "value": 0
              }
            ]
          },
          "unit": "ops"
        },
        "overrides": [
          {
            "matcher": {
              "id": "byRegexp",
              "options": "/alerts=\"true\"/"
            },
            "properties": [
              {
                "id": "color",
                "value": {
                  "fixedColor": "red",
                  "mode": "fixed"
                }
              },
              {
                "id": "custom.lineWidth",
                "value": 3
              }
            ]
          }
        ]
      },
      "gridPos": {
        "h": 8,
        "w": 12,
        "x": 12,
        "y": 26
      },
      "id": 7,
      "options": {
        "legend": {
          "calcs": [
            "lastNotNull",
            "mean"
          ],
          "displayMode": "table",
          "placement": "bottom",
          "showLegend": true
        },
        "tooltip": {
          "hideZeros": false,
          "mode": "multi",
          "sort": "desc"
        }
      },
      "pluginVersion": "12.2.0-17027759091",
      "targets": [
        {
          "datasource": {
            "type": "prometheus",
            "uid": "PBFA97CFB590B2093"
          },
          "editorMode": "code",
          "expr": "sum(rate(rcosmos_axelar_evm_votes_total{alerts=\"true\",network=~\"$network\",validator_address=~\"$validator_address\"}[5m])) by (validator_address) * 60",
          "legendFormat": "Our Validator ({{validator_address}})",
          "range": true,
          "refId": "A"
        },
        {
          "datasource": {
            "type": "prometheus",
            "uid": "PBFA97CFB590B2093"
          },
          "editorMode": "code",
          "expr": "sum(rate(rcosmos_axelar_evm_votes_total{alerts=\"false\",network=~\"$network\",validator_address=~\"$validator_address\"}[5m])) by (validator_address) * 60",
          "legendFormat": "{{validator_address}}",
          "range": true,
          "refId": "B"
        }
      ],
      "title": "Voting Rate (Votes per Minute)",
      "type": "timeseries"
    },
    {
      "datasource": {
        "type": "prometheus",
        "uid": "PBFA97CFB590B2093"
      },
      "description": "",
      "fieldConfig": {
        "defaults": {
          "color": {
            "mode": "palette-classic"
          },
          "custom": {
            "axisBorderShow": false,
            "axisCenteredZero": false,
            "axisColorMode": "text",
            "axisLabel": "",
            "axisPlacement": "auto",
            "barAlignment": 0,
            "barWidthFactor": 0.6,
            "drawStyle": "line",
            "fillOpacity": 10,
            "gradientMode": "none",
            "hideFrom": {
              "legend": false,
              "tooltip": false,
              "viz": false
            },
            "insertNulls": false,
            "lineInterpolation": "linear",
            "lineWidth": 2,
            "pointSize": 5,
            "scaleDistribution": {
              "type": "linear"
            },
            "showPoints": "never",
            "spanNulls": false,
            "stacking": {
              "group": "A",
              "mode": "normal"
            },
            "thresholdsStyle": {
              "mode": "off"
            }
          },
          "mappings": [],
          "thresholds": {
            "mode": "absolute",
            "steps": [
              {
                "color": "green",
                "value": 0
              }
            ]
          },
          "unit": "short"
        },
        "overrides": [
          {
            "matcher": {
              "id": "byRegexp",
              "options": "/Yes/"
            },
            "properties": [
              {
                "id": "color",
                "value": {
                  "fixedColor": "green",
                  "mode": "fixed"
                }
              }
            ]
          },
          {
            "matcher": {
              "id": "byRegexp",
              "options": "/No/"
            },
            "properties": [
              {
                "id": "color",
                "value": {
                  "fixedColor": "red",
                  "mode": "fixed"
                }
              }
            ]
          }
        ]
      },
      "gridPos": {
        "h": 8,
        "w": 12,
        "x": 0,
        "y": 34
      },
      "id": 8,
      "options": {
        "legend": {
          "calcs": [
            "lastNotNull",
            "sum"
          ],
          "displayMode": "table",
          "placement": "bottom",
          "showLegend": true
        },
        "tooltip": {
          "hideZeros": false,
          "mode": "multi",
          "sort": "desc"
        }
      },
      "pluginVersion": "12.2.0-17027759091",
      "targets": [
        {
          "datasource": {
            "type": "prometheus",
            "uid": "PBFA97CFB590B2093"
          },
          "editorMode": "code",
          "expr": "sum(rcosmos_axelar_evm_votes_yes{alerts=\"true\",network=~\"$network\",validator_address=~\"$validator_address\"}) by (validator_address)",
          "legendFormat": "Our Validator - {{validator_address}}",
          "range": true,
          "refId": "A"
        },
        {
          "datasource": {
            "type": "prometheus",
            "uid": "PBFA97CFB590B2093"
          },
          "editorMode": "code",
          "expr": "sum(rcosmos_axelar_evm_votes_yes{alerts=\"false\",network=~\"$network\",validator_address=~\"$validator_address\"}) by (validator_address)",
          "legendFormat": "{{validator_address}}",
          "range": true,
          "refId": "B"
        }
      ],
      "title": "Vote Yes",
      "type": "timeseries"
    },
    {
      "datasource": {
        "type": "prometheus",
        "uid": "PBFA97CFB590B2093"
      },
      "description": "",
      "fieldConfig": {
        "defaults": {
          "color": {
            "mode": "palette-classic"
          },
          "custom": {
            "axisBorderShow": false,
            "axisCenteredZero": false,
            "axisColorMode": "text",
            "axisLabel": "",
            "axisPlacement": "auto",
            "barAlignment": 0,
            "barWidthFactor": 0.6,
            "drawStyle": "line",
            "fillOpacity": 10,
            "gradientMode": "none",
            "hideFrom": {
              "legend": false,
              "tooltip": false,
              "viz": false
            },
            "insertNulls": false,
            "lineInterpolation": "linear",
            "lineWidth": 2,
            "pointSize": 5,
            "scaleDistribution": {
              "type": "linear"
            },
            "showPoints": "never",
            "spanNulls": false,
            "stacking": {
              "group": "A",
              "mode": "normal"
            },
            "thresholdsStyle": {
              "mode": "off"
            }
          },
          "mappings": [],
          "thresholds": {
            "mode": "absolute",
            "steps": [
              {
                "color": "green",
                "value": 0
              }
            ]
          },
          "unit": "short"
        },
        "overrides": [
          {
            "matcher": {
              "id": "byRegexp",
              "options": "/Yes/"
            },
            "properties": [
              {
                "id": "color",
                "value": {
                  "fixedColor": "green",
                  "mode": "fixed"
                }
              }
            ]
          },
          {
            "matcher": {
              "id": "byRegexp",
              "options": "/No/"
            },
            "properties": [
              {
                "id": "color",
                "value": {
                  "fixedColor": "red",
                  "mode": "fixed"
                }
              }
            ]
          }
        ]
      },
      "gridPos": {
        "h": 8,
        "w": 12,
        "x": 12,
        "y": 34
      },
      "id": 9,
      "options": {
        "legend": {
          "calcs": [
            "lastNotNull",
            "sum"
          ],
          "displayMode": "table",
          "placement": "bottom",
          "showLegend": true
        },
        "tooltip": {
          "hideZeros": false,
          "mode": "multi",
          "sort": "desc"
        }
      },
      "pluginVersion": "12.2.0-17027759091",
      "targets": [
        {
          "datasource": {
            "type": "prometheus",
            "uid": "PBFA97CFB590B2093"
          },
          "editorMode": "code",
          "expr": "sum(rcosmos_axelar_evm_votes_no{alerts=\"true\",network=~\"$network\",validator_address=~\"$validator_address\"}) by (validator_address)",
          "legendFormat": "Our Validator - {{validator_address}}",
          "range": true,
          "refId": "A"
        },
        {
          "datasource": {
            "type": "prometheus",
            "uid": "PBFA97CFB590B2093"
          },
          "editorMode": "code",
          "expr": "sum(rcosmos_axelar_evm_votes_no{alerts=\"false\",network=~\"$network\",validator_address=~\"$validator_address\"}) by (validator_address)",
          "legendFormat": "{{validator_address}}",
          "range": true,
          "refId": "B"
        }
      ],
      "title": "Vote No",
      "type": "timeseries"
    },
    {
      "datasource": {
        "type": "prometheus",
        "uid": "PBFA97CFB590B2093"
      },
      "description": "",
      "fieldConfig": {
        "defaults": {
          "color": {
            "mode": "palette-classic"
          },
          "custom": {
            "axisBorderShow": false,
            "axisCenteredZero": false,
            "axisColorMode": "text",
            "axisLabel": "",
            "axisPlacement": "auto",
            "barAlignment": 0,
            "barWidthFactor": 0.6,
            "drawStyle": "line",
            "fillOpacity": 10,
            "gradientMode": "none",
            "hideFrom": {
              "legend": false,
              "tooltip": false,
              "viz": false
            },
            "insertNulls": false,
            "lineInterpolation": "linear",
            "lineWidth": 2,
            "pointSize": 5,
            "scaleDistribution": {
              "type": "linear"
            },
            "showPoints": "never",
            "spanNulls": false,
            "stacking": {
              "group": "A",
              "mode": "normal"
            },
            "thresholdsStyle": {
              "mode": "off"
            }
          },
          "mappings": [],
          "thresholds": {
            "mode": "absolute",
            "steps": [
              {
                "color": "green",
                "value": 0
              }
            ]
          },
          "unit": "short"
        },
        "overrides": [
          {
            "matcher": {
              "id": "byRegexp",
              "options": "/Yes/"
            },
            "properties": [
              {
                "id": "color",
                "value": {
                  "fixedColor": "green",
                  "mode": "fixed"
                }
              }
            ]
          },
          {
            "matcher": {
              "id": "byRegexp",
              "options": "/No/"
            },
            "properties": [
              {
                "id": "color",
                "value": {
                  "fixedColor": "red",
                  "mode": "fixed"
                }
              }
            ]
          }
        ]
      },
      "gridPos": {
        "h": 13,
        "w": 24,
        "x": 0,
        "y": 42
      },
      "id": 10,
      "options": {
        "legend": {
          "calcs": [
            "lastNotNull",
            "sum"
          ],
          "displayMode": "table",
          "placement": "bottom",
          "showLegend": true
        },
        "tooltip": {
          "hideZeros": false,
          "mode": "multi",
          "sort": "desc"
        }
      },
      "pluginVersion": "12.2.0-17027759091",
      "targets": [
        {
          "datasource": {
            "type": "prometheus",
            "uid": "PBFA97CFB590B2093"
          },
          "editorMode": "code",
          "expr": "sum(rcosmos_axelar_evm_votes_total{alerts=\"true\",network=~\"$network\",validator_address=~\"$validator_address\"}) by (sender_chain, recipient_chain, validator_address)",
          "legendFormat": "Our Validator - {{validator_address}} - {{sender_chain}} → {{recipient_chain}}",
          "range": true,
          "refId": "A"
        },
        {
          "datasource": {
            "type": "prometheus",
            "uid": "PBFA97CFB590B2093"
          },
          "editorMode": "code",
          "expr": "sum(rcosmos_axelar_evm_votes_total{alerts=\"false\",network=~\"$network\",validator_address=~\"$validator_address\"}) by (sender_chain, recipient_chain,validator_address)",
          "legendFormat": "Our Validator - {{validator_address}} - {{sender_chain}} → {{recipient_chain}}",
          "range": true,
          "refId": "B"
        }
      ],
      "title": "Vote Yes",
      "type": "timeseries"
    },
    {
      "datasource": {
        "type": "prometheus",
        "uid": "PBFA97CFB590B2093"
      },
      "description": "Total number of votes missed by our validator. Should be 0 if voting correctly. Alert if > 0.",
      "fieldConfig": {
        "defaults": {
          "color": {
            "mode": "thresholds"
          },
          "mappings": [],
          "thresholds": {
            "mode": "absolute",
            "steps": [
              {
                "color": "green",
                "value": 0
              },
              {
                "color": "red",
                "value": 1
              }
            ]
          },
          "unit": "short"
        },
        "overrides": []
      },
      "gridPos": {
        "h": 3,
        "w": 24,
        "x": 0,
        "y": 55
      },
      "id": 11,
      "options": {
        "colorMode": "value",
        "graphMode": "area",
        "justifyMode": "auto",
        "orientation": "auto",
        "percentChangeColorMode": "standard",
        "reduceOptions": {
          "calcs": [
            "lastNotNull"
          ],
          "fields": "",
          "values": false
        },
        "showPercentChange": false,
        "textMode": "auto",
        "wideLayout": true
      },
      "pluginVersion": "12.2.0-17027759091",
      "targets": [
        {
          "datasource": {
            "type": "prometheus",
            "uid": "PBFA97CFB590B2093"
          },
          "editorMode": "code",
          "expr": "sum(rcosmos_axelar_evm_votes_missed{alerts=\"true\",network=~\"$network\",validator_address=~\"$validator_address\"})",
          "legendFormat": "Total Missed Votes",
          "range": true,
          "refId": "A"
        }
      ],
      "title": "Our Validator - Total Missed Votes",
      "type": "stat"
    },
    {
      "datasource": {
        "type": "prometheus",
        "uid": "PBFA97CFB590B2093"
      },
      "description": "Missed votes broken down by sender_chain → recipient_chain pairs. Use this to identify which chain pairs are being missed.",
      "fieldConfig": {
        "defaults": {
          "color": {
            "mode": "thresholds"
          },
          "custom": {
            "align": "auto",
            "cellOptions": {
              "type": "auto"
            },
            "inspect": false
          },
          "mappings": [],
          "thresholds": {
            "mode": "absolute",
            "steps": [
              {
                "color": "green",
                "value": 0
              },
              {
                "color": "red",
                "value": 1
              }
            ]
          }
        },
        "overrides": [
          {
            "matcher": {
              "id": "byName",
              "options": "Missed Votes"
            },
            "properties": [
              {
                "id": "custom.width",
                "value": 150
              }
            ]
          },
          {
            "matcher": {
              "id": "byName",
              "options": "Sender Chain"
            },
            "properties": [
              {
                "id": "custom.width",
                "value": 120
              }
            ]
          },
          {
            "matcher": {
              "id": "byName",
              "options": "Recipient Chain"
            },
            "properties": [
              {
                "id": "custom.width",
                "value": 120
              }
            ]
          }
        ]
      },
      "gridPos": {
        "h": 10,
        "w": 12,
        "x": 0,
        "y": 58
      },
      "id": 12,
      "options": {
        "cellHeight": "sm",
        "footer": {
          "countRows": false,
          "fields": "",
          "reducer": [
            "sum"
          ],
          "show": false
        },
        "showHeader": true,
        "sortBy": [
          {
            "desc": true,
            "displayName": "Missed Votes"
          }
        ]
      },
      "pluginVersion": "12.2.0-17027759091",
      "targets": [
        {
          "datasource": {
            "type": "prometheus",
            "uid": "PBFA97CFB590B2093"
          },
          "editorMode": "code",
          "expr": "sum(rcosmos_axelar_evm_votes_missed{alerts=\"true\",network=~\"$network\",validator_address=~\"$validator_address\",sender_chain!=\"unknown\",recipient_chain!=\"unknown\"}) by (sender_chain, recipient_chain)",
          "format": "table",
          "instant": true,
          "legendFormat": "",
          "refId": "A"
        }
      ],
      "title": "Missed Votes by Chain Pair",
      "transformations": [
        {
          "id": "organize",
          "options": {
            "excludeByName": {
              "Time": true
            },
            "indexByName": {},
            "renameByName": {
              "Value": "Missed Votes",
              "recipient_chain": "Recipient Chain",
              "sender_chain": "Sender Chain"
            }
          }
        }
      ],
      "type": "table"
    },
    {
      "datasource": {
        "type": "prometheus",
        "uid": "PBFA97CFB590B2093"
      },
      "description": "Missed votes over time. Each line represents a different chain pair. Alert if any line increases.",
      "fieldConfig": {
        "defaults": {
          "color": {
            "mode": "palette-classic"
          },
          "custom": {
            "axisBorderShow": false,
            "axisCenteredZero": false,
            "axisColorMode": "text",
            "axisLabel": "Missed Votes",
            "axisPlacement": "auto",
            "barAlignment": 0,
            "barWidthFactor": 0.6,
            "drawStyle": "line",
            "fillOpacity": 10,
            "gradientMode": "none",
            "hideFrom": {
              "legend": false,
              "tooltip": false,
              "viz": false
            },
            "insertNulls": false,
            "lineInterpolation": "linear",
            "lineWidth": 2,
            "pointSize": 5,
            "scaleDistribution": {
              "type": "linear"
            },
            "showPoints": "auto",
            "spanNulls": false,
            "stacking": {
              "group": "A",
              "mode": "none"
            },
            "thresholdsStyle": {
              "mode": "off"
            }
          },
          "mappings": [],
          "thresholds": {
            "mode": "absolute",
            "steps": [
              {
                "color": "green",
                "value": 0
              },
              {
                "color": "red",
                "value": 1
              }
            ]
          },
          "unit": "short"
        },
        "overrides": []
      },
      "gridPos": {
        "h": 10,
        "w": 12,
        "x": 12,
        "y": 58
      },
      "id": 13,
      "options": {
        "legend": {
          "calcs": [
            "lastNotNull",
            "max"
          ],
          "displayMode": "table",
          "placement": "bottom",
          "showLegend": true
        },
        "tooltip": {
          "hideZeros": false,
          "mode": "multi",
          "sort": "desc"
        }
      },
      "pluginVersion": "12.2.0-17027759091",
      "targets": [
        {
          "datasource": {
            "type": "prometheus",
            "uid": "PBFA97CFB590B2093"
          },
          "editorMode": "code",
          "expr": "sum(rcosmos_axelar_evm_votes_missed{alerts=\"true\",network=~\"$network\",validator_address=~\"$validator_address\",sender_chain!=\"unknown\",recipient_chain!=\"unknown\"}) by (sender_chain, recipient_chain)",
          "legendFormat": "{{sender_chain}} → {{recipient_chain}}",
          "range": true,
          "refId": "A"
        }
      ],
      "title": "Missed Votes Over Time by Chain Pair",
      "type": "timeseries"
    },
    {
      "datasource": {
        "type": "prometheus",
        "uid": "PBFA97CFB590B2093"
      },
      "description": "Comprehensive breakdown of votes and missed votes by chain pair for our validator. Shows Yes, No, Late, and Missed votes per chain pair.",
      "fieldConfig": {
        "defaults": {
          "color": {
            "mode": "thresholds"
          },
          "custom": {
            "align": "auto",
            "cellOptions": {
              "type": "auto"
            },
            "inspect": false
          },
          "mappings": [],
          "thresholds": {
            "mode": "absolute",
            "steps": [
              {
                "color": "green",
                "value": 0
              }
            ]
          }
        },
        "overrides": [
          {
            "matcher": {
              "id": "byName",
              "options": "Chain Pair"
            },
            "properties": [
              {
                "id": "custom.width",
                "value": 200
              }
            ]
          },
          {
            "matcher": {
              "id": "byName",
              "options": "Total Votes"
            },
            "properties": [
              {
                "id": "custom.width",
                "value": 100
              },
              {
                "id": "color",
                "value": {
                  "fixedColor": "blue",
                  "mode": "fixed"
                }
              }
            ]
          },
          {
            "matcher": {
              "id": "byName",
              "options": "Yes Votes"
            },
            "properties": [
              {
                "id": "custom.width",
                "value": 100
              },
              {
                "id": "color",
                "value": {
                  "fixedColor": "green",
                  "mode": "fixed"
                }
              }
            ]
          },
          {
            "matcher": {
              "id": "byName",
              "options": "No Votes"
            },
            "properties": [
              {
                "id": "custom.width",
                "value": 100
              },
              {
                "id": "color",
                "value": {
                  "fixedColor": "orange",
                  "mode": "fixed"
                }
              }
            ]
          },
          {
            "matcher": {
              "id": "byName",
              "options": "Late Votes"
            },
            "properties": [
              {
                "id": "custom.width",
                "value": 100
              },
              {
                "id": "color",
                "value": {
                  "fixedColor": "yellow",
                  "mode": "fixed"
                }
              }
            ]
          },
          {
            "matcher": {
              "id": "byName",
              "options": "Missed Votes"
            },
            "properties": [
              {
                "id": "custom.width",
                "value": 100
              },
              {
                "id": "color",
                "value": {
                  "fixedColor": "red",
                  "mode": "fixed"
                }
              },
              {
                "id": "thresholds",
                "value": {
                  "mode": "absolute",
                  "steps": [
                    {
                      "color": "green",
                      "value": 0
                    },
                    {
                      "color": "red",
                      "value": 1
                    }
                  ]
                }
              }
            ]
          }
        ]
      },
      "gridPos": {
        "h": 13,
        "w": 24,
        "x": 0,
        "y": 68
      },
      "id": 14,
      "options": {
        "cellHeight": "sm",
        "footer": {
          "countRows": false,
          "fields": "",
          "reducer": [
            "sum"
          ],
          "show": true
        },
        "showHeader": true,
        "sortBy": [
          {
            "desc": true,
            "displayName": "Missed Votes"
          }
        ]
      },
      "pluginVersion": "12.2.0-17027759091",
      "targets": [
        {
          "datasource": {
            "type": "prometheus",
            "uid": "PBFA97CFB590B2093"
          },
          "editorMode": "code",
          "expr": "sum(rcosmos_axelar_evm_votes_total{alerts=\"true\",network=~\"$network\",validator_address=~\"$validator_address\",sender_chain!=\"unknown\",recipient_chain!=\"unknown\"}) by (sender_chain, recipient_chain)",
          "format": "table",
          "instant": true,
          "legendFormat": "",
          "refId": "A"
        },
        {
          "datasource": {
            "type": "prometheus",
            "uid": "PBFA97CFB590B2093"
          },
          "editorMode": "code",
          "expr": "sum(rcosmos_axelar_evm_votes_yes{alerts=\"true\",network=~\"$network\",validator_address=~\"$validator_address\",sender_chain!=\"unknown\",recipient_chain!=\"unknown\"}) by (sender_chain, recipient_chain)",
          "format": "table",
          "instant": true,
          "legendFormat": "",
          "refId": "B"
        },
        {
          "datasource": {
            "type": "prometheus",
            "uid": "PBFA97CFB590B2093"
          },
          "editorMode": "code",
          "expr": "sum(rcosmos_axelar_evm_votes_no{alerts=\"true\",network=~\"$network\",validator_address=~\"$validator_address\",sender_chain!=\"unknown\",recipient_chain!=\"unknown\"}) by (sender_chain, recipient_chain)",
          "format": "table",
          "instant": true,
          "legendFormat": "",
          "refId": "C"
        },
        {
          "datasource": {
            "type": "prometheus",
            "uid": "PBFA97CFB590B2093"
          },
          "editorMode": "code",
          "expr": "sum(rcosmos_axelar_evm_votes_late{alerts=\"true\",network=~\"$network\",validator_address=~\"$validator_address\",sender_chain!=\"unknown\",recipient_chain!=\"unknown\"}) by (sender_chain, recipient_chain)",
          "format": "table",
          "instant": true,
          "legendFormat": "",
          "refId": "D"
        },
        {
          "datasource": {
            "type": "prometheus",
            "uid": "PBFA97CFB590B2093"
          },
          "editorMode": "code",
          "expr": "sum(rcosmos_axelar_evm_votes_missed{alerts=\"true\",network=~\"$network\",validator_address=~\"$validator_address\",sender_chain!=\"unknown\",recipient_chain!=\"unknown\"}) by (sender_chain, recipient_chain)",
          "format": "table",
          "instant": true,
          "legendFormat": "",
          "refId": "E"
        }
      ],
      "title": "Vote Breakdown by Chain Pair (Our Validator)",
      "transformations": [
        {
          "id": "merge",
          "options": {}
        },
        {
          "id": "organize",
          "options": {
            "excludeByName": {
              "Time": true
            },
            "indexByName": {
              "Value #A": 2,
              "Value #B": 3,
              "Value #C": 4,
              "Value #D": 5,
              "Value #E": 6,
              "recipient_chain": 1,
              "sender_chain": 0
            },
            "renameByName": {
              "Value #A": "Total Votes",
              "Value #B": "Yes Votes",
              "Value #C": "No Votes",
              "Value #D": "Late Votes",
              "Value #E": "Missed Votes",
              "recipient_chain": "Recipient Chain",
              "sender_chain": "Sender Chain"
            }
          }
        }
      ],
      "type": "table"
    }
  ],
  "preload": false,
  "schemaVersion": 41,
  "tags": [
    "axelar",
    "broadcaster"
  ],
  "templating": {
    "list": [
      {
        "current": {
          "text": "All",
          "value": "$__all"
        },
        "datasource": {
          "type": "prometheus",
          "uid": "PBFA97CFB590B2093"
        },
        "definition": "label_values(rcosmos_axelar_evm_polls_total, network)",
        "includeAll": true,
        "label": "Network",
        "multi": true,
        "name": "network",
        "options": [],
        "query": {
          "query": "label_values(rcosmos_axelar_evm_polls_total, network)",
          "refId": "StandardVariableQuery"
        },
        "refresh": 1,
        "regex": "",
        "sort": 1,
        "type": "query"
      },
      {
        "current": {
          "text": "All",
          "value": "$__all"
        },
        "datasource": {
          "type": "prometheus",
          "uid": "PBFA97CFB590B2093"
        },
        "definition": "label_values(rcosmos_axelar_evm_votes_total{network=~\"$network\"}, validator_address)",
        "includeAll": true,
        "label": "Validator Address",
        "multi": true,
        "name": "validator_address",
        "options": [],
        "query": {
          "query": "label_values(rcosmos_axelar_evm_votes_total{network=~\"$network\"}, validator_address)",
          "refId": "StandardVariableQuery"
        },
        "refresh": 1,
        "regex": "",
        "sort": 1,
        "type": "query"
      }
    ]
  },
  "time": {
    "from": "now-1h",
    "to": "now"
  },
  "timepicker": {},
  "timezone": "browser",
  "title": "Axelar Broadcaster - Voting Dashboard",
  "uid": "9b58dc08-1011-4e19-a4d6-44062220d479",
  "version": 1
}